demoterm/__init__.py
demoterm/__main__.py
demoterm-1.1.dist-info/licenses/LICENSE
demoterm-1.1.dist-info/METADATA
demoterm-1.1.dist-info/WHEEL
demoterm-1.1.dist-info/entry_points.txt
demoterm-1.1.dist-info/top_level.txt
demoterm-1.1.dist-info/RECORD
