Metadata-Version: 2.4
Name: demoterm
Version: 1.1
Author-email: "Etienne Dublé (CNRS)" <etienne.duble@imag.fr>
License-Expression: BSD-3-Clause
Keywords: CLI,Demo
Requires-Python: >=3.11
License-File: LICENSE
Provides-Extra: dev
Requires-Dist: build; extra == "dev"
Requires-Dist: twine; extra == "dev"
Dynamic: license-file
